mercury/monitoring/__init__.py
mercury/monitoring/create_tutorials.py
mercury/monitoring/drift/__init__.py
mercury/monitoring/drift/_resampling.py
mercury/monitoring/drift/_vae.py
mercury/monitoring/drift/auto_encoder_drift_detector.py
mercury/monitoring/drift/base.py
mercury/monitoring/drift/chi2_drift_detector.py
mercury/monitoring/drift/density_drift_detector.py
mercury/monitoring/drift/domain_classifier_drift_detector.py
mercury/monitoring/drift/drift_simulation.py
mercury/monitoring/drift/histogram_distance_drift_detector.py
mercury/monitoring/drift/ks_drift_detector.py
mercury/monitoring/drift/metrics.py
mercury/monitoring/estimation/__init__.py
mercury/monitoring/estimation/performance_predictor.py
mercury/monitoring/tutorials/data/winequality/winequality-red.csv
mercury/monitoring/tutorials/data/winequality/winequality-white.csv
mercury/monitoring/tutorials/drift/Autoencoder_Drift_Detection.ipynb
mercury/monitoring/tutorials/drift/Batch_Drift_Detection.ipynb
mercury/monitoring/tutorials/drift/DensityBasedDriftDetection.ipynb
mercury/monitoring/tutorials/drift/bootstrap_eval_metric_drift.ipynb
mercury/monitoring/tutorials/images/drift_example.png
mercury/monitoring/tutorials/performance_prediction/tutorial_estimate_model_performance_without_labels.ipynb
mercury_monitoring-1.1.3.dist-info/LICENSE
mercury_monitoring-1.1.3.dist-info/METADATA
mercury_monitoring-1.1.3.dist-info/WHEEL
mercury_monitoring-1.1.3.dist-info/top_level.txt
mercury_monitoring-1.1.3.dist-info/RECORD
