Metadata-Version: 2.2
Name: mercury-monitoring
Version: 1.1.3
Summary: Mercury's monitoring is a library to perform monitoring testing on models and/or datasets..
Author-email: Mercury Team <mercury.group@bbva.com>
Project-URL: Homepage, https://github.com/BBVA/mercury-monitoring
Project-URL: Bug Tracker, https://github.com/BBVA/mercury-monitoring/issues
Classifier: Programming Language :: Python :: 3
Classifier: License :: OSI Approved :: Apache Software License
Classifier: Operating System :: OS Independent
Requires-Python: >=3.7
License-File: LICENSE
Requires-Dist: matplotlib>=3.0.2
Requires-Dist: pandas>=0.24.2
Requires-Dist: scikit-learn>=0.23.1
Requires-Dist: seaborn
Requires-Dist: mercury-dataschema
Requires-Dist: scipy
Requires-Dist: tensorflow>=1.15
Requires-Dist: matplotlib>=3.0.2
Provides-Extra: dev
Requires-Dist: pytest; extra == "dev"
Requires-Dist: flake8; extra == "dev"
Provides-Extra: doc
Requires-Dist: mkdocs; extra == "doc"
Requires-Dist: mkdocstrings[python]; extra == "doc"
Requires-Dist: mkdocs-material; extra == "doc"
Requires-Dist: mkdocs-minify-plugin==0.5.0; extra == "doc"
Requires-Dist: mkdocs-exclude; extra == "doc"
Requires-Dist: nbconvert; extra == "doc"
